setup.py
njabjrjfnvkzjkcvndfkdjnvkdsbvjksd/__init__.py
njabjrjfnvkzjkcvndfkdjnvkdsbvjksd/corrector.py
njabjrjfnvkzjkcvndfkdjnvkdsbvjksd/data_structurs-DESKTOP-7L67LLS.py
njabjrjfnvkzjkcvndfkdjnvkdsbvjksd/data_structurs.py
njabjrjfnvkzjkcvndfkdjnvkdsbvjksd/detector.py
njabjrjfnvkzjkcvndfkdjnvkdsbvjksd/exceptions.py
njabjrjfnvkzjkcvndfkdjnvkdsbvjksd/occultation-DESKTOP-7L67LLS.py
njabjrjfnvkzjkcvndfkdjnvkdsbvjksd/occultation.py
njabjrjfnvkzjkcvndfkdjnvkdsbvjksd/photometry-DESKTOP-7L67LLS.py
njabjrjfnvkzjkcvndfkdjnvkdsbvjksd/photometry.py
njabjrjfnvkzjkcvndfkdjnvkdsbvjksd/utils.py
njabjrjfnvkzjkcvndfkdjnvkdsbvjksd.egg-info/PKG-INFO
njabjrjfnvkzjkcvndfkdjnvkdsbvjksd.egg-info/SOURCES.txt
njabjrjfnvkzjkcvndfkdjnvkdsbvjksd.egg-info/dependency_links.txt
njabjrjfnvkzjkcvndfkdjnvkdsbvjksd.egg-info/requires.txt
njabjrjfnvkzjkcvndfkdjnvkdsbvjksd.egg-info/top_level.txt