Metadata-Version: 1.1
Name: njabjrjfnvkzjkcvndfkdjnvkdsbvjksd
Version: 0.0.13
Summary: Testing installation of Package
Home-page: UNKNOWN
Author: Antoine Choukroun
Author-email: antcho1@amu.edu.pl
License: MIT
Keywords: pypi,astePhot,tutorial
Platform: UNKNOWN
Classifier: License :: OSI Approved :: MIT License
Classifier: Programming Language :: Python :: 3
Classifier: Programming Language :: Python :: 3.7
Classifier: Programming Language :: Python :: 3.8
Classifier: Programming Language :: Python :: 3.9
